onedriveignore/__init__.py
onedriveignore/one_drive_ignore.py
onedrive_ignore-0.0.4.dist-info/LICENSE.txt
onedrive_ignore-0.0.4.dist-info/METADATA
onedrive_ignore-0.0.4.dist-info/WHEEL
onedrive_ignore-0.0.4.dist-info/entry_points.txt
onedrive_ignore-0.0.4.dist-info/top_level.txt
onedrive_ignore-0.0.4.dist-info/RECORD
