Metadata-Version: 2.1
Name: onedrive-ignore
Version: 0.0.4
Summary: OneDrive ignore files
Home-page: https://github.com/kodaman2/OneDriveIgnore
Author: Fernando Balandran
Author-email: fernandobe+git@protonmail.com
License: UNKNOWN
Platform: UNKNOWN
Classifier: Programming Language :: Python :: 3
Classifier: License :: OSI Approved :: MIT License
Classifier: Operating System :: OS Independent
